README.rst
setup.py
a8ctl/__init__.py
a8ctl.egg-info/PKG-INFO
a8ctl.egg-info/SOURCES.txt
a8ctl.egg-info/dependency_links.txt
a8ctl.egg-info/entry_points.txt
a8ctl.egg-info/requires.txt
a8ctl.egg-info/top_level.txt
a8ctl/v1/__init__.py
a8ctl/v1/a8ctl.py
a8ctl/v1/commands.py
gremlin/__init__.py
gremlin/applicationgraph.py
gremlin/assertionchecker_a8.py
gremlin/failuregenerator_a8.py