Metadata-Version: 1.0
Name: a8ctl
Version: 0.3
Summary: Amalgam8 Command Line Interface
Home-page: https://github.com/amalgam8/a8ctl
Author: Amalgam8 Team
Author-email: UNKNOWN
License: Apache Software License V2
Platform: UNKNOWN
